pytorch_lightning_template/__init__.py
pytorch_lightning_template/example.py
pytorch_lightning_template-0.1.1.dist-info/LICENSE
pytorch_lightning_template-0.1.1.dist-info/METADATA
pytorch_lightning_template-0.1.1.dist-info/WHEEL
pytorch_lightning_template-0.1.1.dist-info/top_level.txt
pytorch_lightning_template-0.1.1.dist-info/RECORD
