Metadata-Version: 2.1
Name: pytorch-lightning-template
Version: 0.1.1
Summary: A thin wrapper for Pytorch Lightning, inspired by Keras API
Home-page: https://github.com/smpurkis/autocompile
Author: Sam Purkis
Author-email: sam.purkis@hotmail.co.uk
License: UNKNOWN
Project-URL: Bug Tracker, https://github.com/smpurkis/autocompile/issues
Platform: UNKNOWN
Classifier: Programming Language :: Python :: 3
Classifier: License :: OSI Approved :: MIT License
Classifier: Operating System :: OS Independent
Requires-Python: >=3.6
License-File: LICENSE
Requires-Dist: pytorch-lightning
Requires-Dist: torch
Requires-Dist: torchinfo
